{
  "status_counts": {
    "resolved_internal": 30418,
    "unresolved_no_target_code": 3284,
    "unresolved_zero_code": 1018,
    "resolved_multi_exact_word_backfill": 95,
    "resolved_exact_word_backfill": 130,
    "unresolved_missing_entry": 1
  },
  "unresolved_total": 4303,
  "unresolved_buckets": {
    "source_ambiguous": 4302,
    "no_xml_hint": 1
  },
  "samples": {
    "source_explicit_single": [],
    "source_explicit_multi": [],
    "source_ambiguous": [
      {
        "entry_id": "14064",
        "entry_word": "신분",
        "related_form": "신분적"
      },
      {
        "entry_id": "14065",
        "entry_word": "신비",
        "related_form": "신비적"
      },
      {
        "entry_id": "14080",
        "entry_word": "실감",
        "related_form": "실감적"
      },
      {
        "entry_id": "14095",
        "entry_word": "영웅",
        "related_form": "영웅적"
      },
      {
        "entry_id": "14095",
        "entry_word": "영웅",
        "related_form": "영웅적"
      },
      {
        "entry_id": "14130",
        "entry_word": "예감",
        "related_form": "예감되다"
      },
      {
        "entry_id": "14138",
        "entry_word": "오로지",
        "related_form": "오로지하다"
      },
      {
        "entry_id": "14142",
        "entry_word": "오락",
        "related_form": "오락하다"
      },
      {
        "entry_id": "14142",
        "entry_word": "오락",
        "related_form": "오락하다"
      },
      {
        "entry_id": "14143",
        "entry_word": "예비",
        "related_form": "예비적"
      },
      {
        "entry_id": "14145",
        "entry_word": "예산",
        "related_form": "예산하다"
      },
      {
        "entry_id": "14145",
        "entry_word": "예산",
        "related_form": "예산하다"
      },
      {
        "entry_id": "14148",
        "entry_word": "예선",
        "related_form": "예선하다"
      },
      {
        "entry_id": "14160",
        "entry_word": "간증",
        "related_form": "간증되다"
      },
      {
        "entry_id": "14160",
        "entry_word": "간증",
        "related_form": "간증하다"
      },
      {
        "entry_id": "14160",
        "entry_word": "간증",
        "related_form": "간증되다"
      },
      {
        "entry_id": "14160",
        "entry_word": "간증",
        "related_form": "간증하다"
      },
      {
        "entry_id": "14179",
        "entry_word": "과언",
        "related_form": "과언하다"
      },
      {
        "entry_id": "14183",
        "entry_word": "꼼짝",
        "related_form": "꼼짝거리다"
      },
      {
        "entry_id": "14183",
        "entry_word": "꼼짝",
        "related_form": "꼼작대다"
      }
    ],
    "no_xml_hint": [
      {
        "entry_id": "14936",
        "entry_word": "가뭇가뭇하다",
        "related_form": "가뭇가뭇"
      }
    ]
  }
}
